{
  "Root": {
    "Children": {
      "Dwarf": {
        "Children": {},
        "Transform": {
          "Euler": {
            "X": 9.562092E-05,
            "Y": 1.526625E-12,
            "Z": 5.122473E-06
          },
          "Scale": {
            "X": 1.0,
            "Y": 1.0,
            "Z": 1.0
          },
          "Rot": {
            "X": 8.34465E-07,
            "Y": -5.062617E-14,
            "Z": -4.470282E-08,
            "W": 0.99998194
          }
        },
        "Components": {
          "Model": {
            "Path": "Models/WizardGnome/WizardGnome.fbx",
            "Color": {
              "R": 255,
              "G": 255,
              "B": 255,
              "A": 255
            },
            "AlphaCutoff": 0.5
          },
          "Animation": {
            "Path": "Models/WizardGnome/WizardGnome.fbx",
            "IsPlaying": true,
            "Looping": true
          },
          "Script": {
            "Path": "Scripts/Player.lua"
          },
          "Rigidbody": {
            "Friction": 0.0,
            "Bounciness": 0.0,
            "FrictionCombine": 1,
            "BounceCombine": 1,
            "FreezeRot": {
              "X": true,
              "Y": true,
              "Z": true
            }
          },
          "SphereCollider": {
            "Radius": 0.3,
            "Center": {
              "Y": 0.3
            }
          }
        }
      },
      "Environment": {
        "Children": {
          "Map": {
            "Children": {
              "Block": {
                "Children": {},
                "Transform": {
                  "Pos": {
                    "Y": -6.0
                  },
                  "Scale": {
                    "X": 0.03,
                    "Y": 0.03,
                    "Z": 0.03
                  },
                  "Rot": {
                    "W": 1.0,
                    "IsIdentity": true
                  }
                },
                "Components": {
                  "Model": {
                    "Path": "Models/KenneyPlatformerKit/BlockGrassOverhangLargeTall.fbx",
                    "Color": {
                      "R": 255,
                      "G": 255,
                      "B": 255,
                      "A": 255
                    },
                    "AlphaCutoff": 0.5
                  },
                  "BoxCollider": {
                    "Size": {
                      "X": 200.0,
                      "Y": 200.0,
                      "Z": 200.0
                    },
                    "Center": {
                      "Y": 100.0
                    }
                  },
                  "Rigidbody": {
                    "IsStatic": true,
                    "Gravity": false,
                    "Bounciness": 0.0
                  }
                }
              }
            },
            "Transform": {
              "Scale": {
                "X": 1.0,
                "Y": 1.0,
                "Z": 1.0
              },
              "Rot": {
                "W": 1.0,
                "IsIdentity": true
              }
            },
            "Components": {}
          }
        },
        "Transform": {
          "Scale": {
            "X": 1.0,
            "Y": 1.0,
            "Z": 1.0
          },
          "Rot": {
            "W": 1.0,
            "IsIdentity": true
          }
        },
        "Components": {}
      },
      "Camera": {
        "Children": {},
        "Transform": {
          "Pos": {
            "Y": 3.0,
            "Z": -3.0
          },
          "Euler": {
            "X": 22.5
          },
          "Scale": {
            "X": 1.0,
            "Y": 1.0,
            "Z": 1.0
          },
          "Rot": {
            "X": 0.19509032,
            "W": 0.98078525
          }
        },
        "Components": {
          "Camera": {
            "Fov": 60.0,
            "NearClip": 0.01,
            "FarClip": 1000.0
          }
        }
      },
      "Directional Light": {
        "Children": {},
        "Transform": {
          "Pos": {
            "Y": 3.4
          },
          "Euler": {
            "X": -56.309933,
            "Y": 89.95154
          },
          "Scale": {
            "X": 1.0,
            "Y": 1.0,
            "Z": 1.0
          },
          "Rot": {
            "X": 0.270598,
            "Y": -0.65328145,
            "Z": 0.27059805,
            "W": 0.6532813
          }
        },
        "Components": {
          "Light": {
            "Type": 0,
            "ScytheColor": {
              "R": 255,
              "G": 255,
              "B": 255,
              "A": 255
            },
            "Intensity": 10.0,
            "Range": 10.0,
            "ShadowStrength": 1.0
          }
        }
      }
    },
    "Transform": {
      "Scale": {
        "X": 1.0,
        "Y": 1.0,
        "Z": 1.0
      },
      "Rot": {
        "W": 1.0,
        "IsIdentity": true
      }
    },
    "Components": {}
  },
  "EditorCamera": {
    "Position": {
      "X": -2.061951,
      "Y": 1.7919356,
      "Z": 3.336801
    },
    "Rotation": {
      "X": -0.27384126,
      "Y": 33.85716
    }
  }
}